Calpylus/__init__.py
Calpylus/calculus.py
Calpylus/cli/__init__.py
Calpylus/cli/calpylus_cli.py
Calpylus/core/__init__.py
Calpylus/core/derivative.py
Calpylus/core/domain.py
Calpylus/core/graphing.py
Calpylus/core/integrals.py
Calpylus/core/limits.py
Calpylus/core/multivariable.py
Calpylus/core/range_finder.py
Calpylus/core/series.py
Calpylus/core/simplifier.py
Calpylus/core/symbols.py
Calpylus/utils/__init__.py
Calpylus/utils/checks.py
Calpylus/utils/extrema.py
Calpylus/utils/numerics.py
calpylus-0.0.5.dist-info/licenses/LICENSE
calpylus-0.0.5.dist-info/METADATA
calpylus-0.0.5.dist-info/WHEEL
calpylus-0.0.5.dist-info/top_level.txt
calpylus-0.0.5.dist-info/RECORD
