Metadata-Version: 2.4
Name: Calpylus
Version: 0.0.5
Summary: Calpylus is a powerful calculus toolkit built in Python.
Home-page: https://github.com/mahfuz0712/Calpylus.git
Author: Mohammad Mahfuz Rahman
Author-email: Mohammad Mahfuz Rahman <mahfuzrahman0712@gmail.com>
License: MIT
Project-URL: Homepage, https://github.com/mahfuz0712/Calpylus
Classifier: Programming Language :: Python :: 3
Classifier: Operating System :: OS Independent
Requires-Python: >=3.9
License-File: LICENSE
Requires-Dist: setuptools>=80.8.0
Requires-Dist: twine>=4.0.2
Requires-Dist: matplotlib
Requires-Dist: sympy
Dynamic: author
Dynamic: home-page
Dynamic: license-file
Dynamic: requires-python
